{
  "warnings": [
    {
      "file": "/Users/robbie/Programs/4thA/ZeroDark.cloud/ZeroDark.cloud/Constants/ZDCConstants.h",
      "line": 203,
      "symbol": "kZDCCloudRcrd_UserID",
      "symbol_kind": "sourcekitten.source.lang.objc.decl.constant",
      "warning": "undocumented"
    },
    {
      "file": "/Users/robbie/Programs/4thA/ZeroDark.cloud/ZeroDark.cloud/Constants/ZDCConstants.h",
      "line": 204,
      "symbol": "kZDCCloudRcrd_Auth0ID",
      "symbol_kind": "sourcekitten.source.lang.objc.decl.constant",
      "warning": "undocumented"
    },
    {
      "file": "/Users/robbie/Programs/4thA/ZeroDark.cloud/ZeroDark.cloud/Constants/ZDCConstants.h",
      "line": 208,
      "symbol": "kAuth04thA_AppClientID",
      "symbol_kind": "sourcekitten.source.lang.objc.decl.constant",
      "warning": "undocumented"
    },
    {
      "file": "/Users/robbie/Programs/4thA/ZeroDark.cloud/ZeroDark.cloud/Constants/ZDCConstants.h",
      "line": 209,
      "symbol": "kAuth04thADomain",
      "symbol_kind": "sourcekitten.source.lang.objc.decl.constant",
      "warning": "undocumented"
    },
    {
      "file": "/Users/robbie/Programs/4thA/ZeroDark.cloud/ZeroDark.cloud/Constants/ZDCConstants.h",
      "line": 213,
      "symbol": "kAuth04thAUserDomain",
      "symbol_kind": "sourcekitten.source.lang.objc.decl.constant",
      "warning": "undocumented"
    },
    {
      "file": "/Users/robbie/Programs/4thA/ZeroDark.cloud/ZeroDark.cloud/Constants/ZDCConstants.h",
      "line": 214,
      "symbol": "kAuth04thARecoveryDomain",
      "symbol_kind": "sourcekitten.source.lang.objc.decl.constant",
      "warning": "undocumented"
    },
    {
      "file": "/Users/robbie/Programs/4thA/ZeroDark.cloud/ZeroDark.cloud/Constants/ZDCConstants.h",
      "line": 216,
      "symbol": "kAuth0DBConnection_UserAuth",
      "symbol_kind": "sourcekitten.source.lang.objc.decl.constant",
      "warning": "undocumented"
    },
    {
      "file": "/Users/robbie/Programs/4thA/ZeroDark.cloud/ZeroDark.cloud/Constants/ZDCConstants.h",
      "line": 217,
      "symbol": "kAuth0DBConnection_Recovery",
      "symbol_kind": "sourcekitten.source.lang.objc.decl.constant",
      "warning": "undocumented"
    },
    {
      "file": "/Users/robbie/Programs/4thA/ZeroDark.cloud/ZeroDark.cloud/Constants/ZDCConstants.h",
      "line": 220,
      "symbol": "kZDCFileExtension_ActivationCode",
      "symbol_kind": "sourcekitten.source.lang.objc.decl.constant",
      "warning": "undocumented"
    },
    {
      "file": "/Users/robbie/Programs/4thA/ZeroDark.cloud/ZeroDark.cloud/Delegate/ZDCAudit.h",
      "line": 14,
      "symbol": "ZDCAudit",
      "symbol_kind": "sourcekitten.source.lang.objc.decl.class",
      "warning": "undocumented"
    },
    {
      "file": "/Users/robbie/Programs/4thA/ZeroDark.cloud/ZeroDark.cloud/Managers/ZDCDatabaseManager.h",
      "line": 112,
      "symbol": "Ext_View_SplitKeys_Date",
      "symbol_kind": "sourcekitten.source.lang.objc.decl.constant",
      "warning": "undocumented"
    },
    {
      "file": "/Users/robbie/Programs/4thA/ZeroDark.cloud/ZeroDark.cloud/Managers/ZDCRestManager.h",
      "line": 530,
      "symbol": "ZDCRestManager.-fetchPreviousBilling:withYear:month:completionQueue:completionBlock:",
      "symbol_kind": "sourcekitten.source.lang.objc.decl.method.instance",
      "warning": "undocumented"
    },
    {
      "file": "/Users/robbie/Programs/4thA/ZeroDark.cloud/ZeroDark.cloud/Managers/ZDCRestManager.h",
      "line": 537,
      "symbol": "ZDCRestManager.-productPurchasedByUser:productIdentifier:transactionIdentifier:appStoreReceipt:completionQueue:completionBlock:",
      "symbol_kind": "sourcekitten.source.lang.objc.decl.method.instance",
      "warning": "undocumented"
    },
    {
      "file": "/Users/robbie/Programs/4thA/ZeroDark.cloud/ZeroDark.cloud/Managers/ZDCSyncManager.h",
      "line": 77,
      "symbol": "kLocalUserIDKey",
      "symbol_kind": "sourcekitten.source.lang.objc.decl.constant",
      "warning": "undocumented"
    },
    {
      "file": "/Users/robbie/Programs/4thA/ZeroDark.cloud/ZeroDark.cloud/Managers/ZDCSyncManager.h",
      "line": 78,
      "symbol": "kAppIDKey",
      "symbol_kind": "sourcekitten.source.lang.objc.decl.constant",
      "warning": "undocumented"
    },
    {
      "file": "/Users/robbie/Programs/4thA/ZeroDark.cloud/ZeroDark.cloud/Managers/ZDCSyncManager.h",
      "line": 79,
      "symbol": "kPullResultKey",
      "symbol_kind": "sourcekitten.source.lang.objc.decl.constant",
      "warning": "undocumented"
    },
    {
      "file": "/Users/robbie/Programs/4thA/ZeroDark.cloud/ZeroDark.cloud/Managers/ZDCUITools.h",
      "line": 22,
      "symbol": "ZDCAccountSetupViewControllerProxy",
      "symbol_kind": "sourcekitten.source.lang.objc.decl.class",
      "warning": "undocumented"
    },
    {
      "file": "/Users/robbie/Programs/4thA/ZeroDark.cloud/ZeroDark.cloud/Managers/ZDCUITools.h",
      "line": 23,
      "symbol": "ZDCAccountSetupViewControllerProxy.-pushCreateAccount",
      "symbol_kind": "sourcekitten.source.lang.objc.decl.method.instance",
      "warning": "undocumented"
    },
    {
      "file": "/Users/robbie/Programs/4thA/ZeroDark.cloud/ZeroDark.cloud/Managers/ZDCUITools.h",
      "line": 24,
      "symbol": "ZDCAccountSetupViewControllerProxy.-pushSignInToAccount",
      "symbol_kind": "sourcekitten.source.lang.objc.decl.method.instance",
      "warning": "undocumented"
    },
    {
      "file": "/Users/robbie/Programs/4thA/ZeroDark.cloud/ZeroDark.cloud/Managers/ZDCUITools.h",
      "line": 38,
      "symbol": "accountSetupViewCompletionHandler",
      "symbol_kind": "sourcekitten.source.lang.objc.decl.typedef",
      "warning": "undocumented"
    },
    {
      "file": "/Users/robbie/Programs/4thA/ZeroDark.cloud/ZeroDark.cloud/Managers/ZDCUITools.h",
      "line": 129,
      "symbol": "SharedUsersViewCompletionHandler",
      "symbol_kind": "sourcekitten.source.lang.objc.decl.typedef",
      "warning": "undocumented"
    },
    {
      "file": "/Users/robbie/Programs/4thA/ZeroDark.cloud/ZeroDark.cloud/Managers/ZDCUserManager.h",
      "line": 119,
      "symbol": "ZDCUserDisplay.userID",
      "symbol_kind": "sourcekitten.source.lang.objc.decl.property",
      "warning": "undocumented"
    },
    {
      "file": "/Users/robbie/Programs/4thA/ZeroDark.cloud/ZeroDark.cloud/Managers/ZDCUserManager.h",
      "line": 120,
      "symbol": "ZDCUserDisplay.displayName",
      "symbol_kind": "sourcekitten.source.lang.objc.decl.property",
      "warning": "undocumented"
    },
    {
      "file": "/Users/robbie/Programs/4thA/ZeroDark.cloud/ZeroDark.cloud/Managers/ZDCUserSearchManager.h",
      "line": 34,
      "symbol": "ZDCSearchResultStage.ZDCSearchResultStage_Database",
      "symbol_kind": "sourcekitten.source.lang.objc.decl.enumcase",
      "warning": "undocumented"
    },
    {
      "file": "/Users/robbie/Programs/4thA/ZeroDark.cloud/ZeroDark.cloud/Managers/ZDCUserSearchManager.h",
      "line": 35,
      "symbol": "ZDCSearchResultStage.ZDCSearchResultStage_Cache",
      "symbol_kind": "sourcekitten.source.lang.objc.decl.enumcase",
      "warning": "undocumented"
    },
    {
      "file": "/Users/robbie/Programs/4thA/ZeroDark.cloud/ZeroDark.cloud/Managers/ZDCUserSearchManager.h",
      "line": 36,
      "symbol": "ZDCSearchResultStage.ZDCSearchResultStage_Server",
      "symbol_kind": "sourcekitten.source.lang.objc.decl.enumcase",
      "warning": "undocumented"
    },
    {
      "file": "/Users/robbie/Programs/4thA/ZeroDark.cloud/ZeroDark.cloud/Managers/ZDCUserSearchManager.h",
      "line": 37,
      "symbol": "ZDCSearchResultStage.ZDCSearchResultStage_Done",
      "symbol_kind": "sourcekitten.source.lang.objc.decl.enumcase",
      "warning": "undocumented"
    },
    {
      "file": "/Users/robbie/Programs/4thA/ZeroDark.cloud/ZeroDark.cloud/Model/Keys/ZDCSymmetricKey.h",
      "line": 26,
      "symbol": "ZDCSymmetricKey.+keyWithString:passCode:",
      "symbol_kind": "sourcekitten.source.lang.objc.decl.method.class",
      "warning": "undocumented"
    },
    {
      "file": "/Users/robbie/Programs/4thA/ZeroDark.cloud/ZeroDark.cloud/Model/Keys/ZDCSymmetricKey.h",
      "line": 29,
      "symbol": "ZDCSymmetricKey.+keyWithS4Key:storageKey:",
      "symbol_kind": "sourcekitten.source.lang.objc.decl.method.class",
      "warning": "undocumented"
    },
    {
      "file": "/Users/robbie/Programs/4thA/ZeroDark.cloud/ZeroDark.cloud/Model/Keys/ZDCSymmetricKey.h",
      "line": 32,
      "symbol": "ZDCSymmetricKey.-initWithUUID:keyJSON:",
      "symbol_kind": "sourcekitten.source.lang.objc.decl.method.instance",
      "warning": "undocumented"
    },
    {
      "file": "/Users/robbie/Programs/4thA/ZeroDark.cloud/ZeroDark.cloud/Model/Keys/ZDCSymmetricKey.h",
      "line": 35,
      "symbol": "ZDCSymmetricKey.uuid",
      "symbol_kind": "sourcekitten.source.lang.objc.decl.property",
      "warning": "undocumented"
    },
    {
      "file": "/Users/robbie/Programs/4thA/ZeroDark.cloud/ZeroDark.cloud/Model/Users/Utilities/ZDCBlockchainProof.h",
      "line": 20,
      "symbol": "ZDCBlockchainProof.merkleTreeRoot",
      "symbol_kind": "sourcekitten.source.lang.objc.decl.property",
      "warning": "undocumented"
    },
    {
      "file": "/Users/robbie/Programs/4thA/ZeroDark.cloud/ZeroDark.cloud/Model/Users/Utilities/ZDCBlockchainProof.h",
      "line": 22,
      "symbol": "ZDCBlockchainProof.blockNumber",
      "symbol_kind": "sourcekitten.source.lang.objc.decl.property",
      "warning": "undocumented"
    },
    {
      "file": "/Users/robbie/Programs/4thA/ZeroDark.cloud/ZeroDark.cloud/Model/Users/Utilities/ZDCBlockchainProof.h",
      "line": 24,
      "symbol": "ZDCBlockchainProof.merkleTreeFile_pubKey",
      "symbol_kind": "sourcekitten.source.lang.objc.decl.property",
      "warning": "undocumented"
    },
    {
      "file": "/Users/robbie/Programs/4thA/ZeroDark.cloud/ZeroDark.cloud/Model/Users/Utilities/ZDCBlockchainProof.h",
      "line": 25,
      "symbol": "ZDCBlockchainProof.merkleTreeFile_keyID",
      "symbol_kind": "sourcekitten.source.lang.objc.decl.property",
      "warning": "undocumented"
    },
    {
      "file": "/Users/robbie/Programs/4thA/ZeroDark.cloud/ZeroDark.cloud/Model/Users/Utilities/ZDCUserIdentity.h",
      "line": 14,
      "symbol": "ZDCUserIdentity",
      "symbol_kind": "sourcekitten.source.lang.objc.decl.class",
      "warning": "undocumented"
    },
    {
      "file": "/Users/robbie/Programs/4thA/ZeroDark.cloud/ZeroDark.cloud/Model/Users/ZDCLocalUser.h",
      "line": 13,
      "symbol": "kS4LocalUser_shelflife",
      "symbol_kind": "sourcekitten.source.lang.objc.decl.constant",
      "warning": "undocumented"
    },
    {
      "file": "/Users/robbie/Programs/4thA/ZeroDark.cloud/ZeroDark.cloud/Model/Users/ZDCLocalUser.h",
      "line": 83,
      "symbol": "ZDCLocalUser.isPayingCustomer",
      "symbol_kind": "sourcekitten.source.lang.objc.decl.property",
      "warning": "undocumented"
    },
    {
      "file": "/Users/robbie/Programs/4thA/ZeroDark.cloud/ZeroDark.cloud/Model/Users/ZDCLocalUser.h",
      "line": 97,
      "symbol": "ZDCLocalUser.activationDate",
      "symbol_kind": "sourcekitten.source.lang.objc.decl.property",
      "warning": "undocumented"
    },
    {
      "file": "/Users/robbie/Programs/4thA/ZeroDark.cloud/ZeroDark.cloud/Model/Users/ZDCLocalUser.h",
      "line": 99,
      "symbol": "ZDCLocalUser.auth0_primary",
      "symbol_kind": "sourcekitten.source.lang.objc.decl.property",
      "warning": "undocumented"
    },
    {
      "file": "/Users/robbie/Programs/4thA/ZeroDark.cloud/ZeroDark.cloud/Streams/ZDCCacheFileHeader.h",
      "line": 38,
      "symbol": "ZDCCacheFileHeader",
      "symbol_kind": "sourcekitten.source.lang.objc.decl.typedef",
      "warning": "undocumented"
    },
    {
      "file": "/Users/robbie/Programs/4thA/ZeroDark.cloud/ZeroDark.cloud/Streams/ZDCCloudFileHeader.h",
      "line": 51,
      "symbol": "ZDCCloudFileHeader",
      "symbol_kind": "sourcekitten.source.lang.objc.decl.typedef",
      "warning": "undocumented"
    },
    {
      "file": "/Users/robbie/Programs/4thA/ZeroDark.cloud/ZeroDark.cloud/Utilities/BIP39Mnemonic.h",
      "line": 15,
      "symbol": "Mnemonic_Algorithm",
      "symbol_kind": "sourcekitten.source.lang.objc.decl.enum",
      "warning": "undocumented"
    },
    {
      "file": "/Users/robbie/Programs/4thA/ZeroDark.cloud/ZeroDark.cloud/Utilities/BIP39Mnemonic.h",
      "line": 15,
      "symbol": "Mnemonic_Algorithm",
      "symbol_kind": "sourcekitten.source.lang.objc.decl.typedef",
      "warning": "undocumented"
    },
    {
      "file": "/Users/robbie/Programs/4thA/ZeroDark.cloud/ZeroDark.cloud/Utilities/BIP39Mnemonic.h",
      "line": 16,
      "symbol": "Mnemonic_Algorithm.Mnemonic_Storm4",
      "symbol_kind": "sourcekitten.source.lang.objc.decl.enumcase",
      "warning": "undocumented"
    },
    {
      "file": "/Users/robbie/Programs/4thA/ZeroDark.cloud/ZeroDark.cloud/Utilities/BIP39Mnemonic.h",
      "line": 17,
      "symbol": "Mnemonic_Algorithm.Mnemonic_ZDC",
      "symbol_kind": "sourcekitten.source.lang.objc.decl.enumcase",
      "warning": "undocumented"
    },
    {
      "file": "/Users/robbie/Programs/4thA/ZeroDark.cloud/ZeroDark.cloud/Utilities/BIP39Mnemonic.h",
      "line": 18,
      "symbol": "Mnemonic_Algorithm.Mnemonic_Invalid",
      "symbol_kind": "sourcekitten.source.lang.objc.decl.enumcase",
      "warning": "undocumented"
    }
  ],
  "source_directory": "/Users/robbie/Programs/4thA/ZeroDark.cloud"
}